pulpcore/__init__.py
pulpcore/client/__init__.py
pulpcore/client/pulp_ansible/__init__.py
pulpcore/client/pulp_ansible/api_client.py
pulpcore/client/pulp_ansible/api_response.py
pulpcore/client/pulp_ansible/configuration.py
pulpcore/client/pulp_ansible/exceptions.py
pulpcore/client/pulp_ansible/py.typed
pulpcore/client/pulp_ansible/rest.py
pulpcore/client/pulp_ansible/api/__init__.py
pulpcore/client/pulp_ansible/api/ansible_collections_api.py
pulpcore/client/pulp_ansible/api/ansible_copy_api.py
pulpcore/client/pulp_ansible/api/api_plugin_ansible_search_collection_versions_api.py
pulpcore/client/pulp_ansible/api/api_roles_api.py
pulpcore/client/pulp_ansible/api/collection_import_api.py
pulpcore/client/pulp_ansible/api/content_collection_deprecations_api.py
pulpcore/client/pulp_ansible/api/content_collection_marks_api.py
pulpcore/client/pulp_ansible/api/content_collection_signatures_api.py
pulpcore/client/pulp_ansible/api/content_collection_versions_api.py
pulpcore/client/pulp_ansible/api/content_namespaces_api.py
pulpcore/client/pulp_ansible/api/content_roles_api.py
pulpcore/client/pulp_ansible/api/distributions_ansible_api.py
pulpcore/client/pulp_ansible/api/pulp_ansible_api_api.py
pulpcore/client/pulp_ansible/api/pulp_ansible_api_v3_api.py
pulpcore/client/pulp_ansible/api/pulp_ansible_api_v3_artifacts_collections_api.py
pulpcore/client/pulp_ansible/api/pulp_ansible_api_v3_collection_versions_all_api.py
pulpcore/client/pulp_ansible/api/pulp_ansible_api_v3_collections_all_api.py
pulpcore/client/pulp_ansible/api/pulp_ansible_api_v3_collections_api.py
pulpcore/client/pulp_ansible/api/pulp_ansible_api_v3_collections_versions_api.py
pulpcore/client/pulp_ansible/api/pulp_ansible_api_v3_collections_versions_docs_blob_api.py
pulpcore/client/pulp_ansible/api/pulp_ansible_api_v3_namespaces_api.py
pulpcore/client/pulp_ansible/api/pulp_ansible_api_v3_plugin_ansible_client_configuration_api.py
pulp_ansible_client-0.29.0.dist-info/METADATA
pulp_ansible_client-0.29.0.dist-info/WHEEL
pulp_ansible_client-0.29.0.dist-info/top_level.txt
pulp_ansible_client-0.29.0.dist-info/RECORD
