Metadata-Version: 2.4
Name: pulp_ansible-client
Version: 0.29.0
Summary: Pulp 3 API
Home-page: 
Author: Pulp Team
Author-email: Pulp Team <pulp-list@redhat.com>
License: GPL-2.0-or-later
Project-URL: Repository, https://github.com/GIT_USER_ID/GIT_REPO_ID
Keywords: OpenAPI,OpenAPI-Generator,Pulp 3 API
Requires-Python: >= 3.9
Requires-Dist: urllib3<3.0.0,>=2.1.0
Requires-Dist: python-dateutil>=2.8.2
Requires-Dist: pydantic>=2
Requires-Dist: typing-extensions>=4.7.1
Requires-Dist: lazy-imports<2,>=1
Dynamic: author
Dynamic: requires-python
